reg_tables/__init__.py
reg_tables/main.py
reg_tables/utils.py
reg_tables-0.1.12.dist-info/LICENSE
reg_tables-0.1.12.dist-info/METADATA
reg_tables-0.1.12.dist-info/WHEEL
reg_tables-0.1.12.dist-info/top_level.txt
reg_tables-0.1.12.dist-info/RECORD
