Metadata-Version: 2.1
Name: reg-tables
Version: 0.1.12
Summary: A simple linearmodels extension to run panel regressions with different specifications and export the results in a professional-looking latex table
Home-page: https://www.abarbon.com
Download-URL: https://github.com/AndreaBarbon/reg_tables/archive/refs/tags/0.0.5.tar.gz
Author: Andrea Barbon, Kirill Kazakov
Author-email: andrea.3arbon@gmail.com
License: MIT
Keywords: Linear models,regression table
Classifier: Development Status :: 3 - Alpha
Classifier: Intended Audience :: Education
Classifier: Intended Audience :: Science/Research
Classifier: Programming Language :: Python :: 3
Classifier: License :: OSI Approved :: MIT License
Classifier: Operating System :: OS Independent
Requires-Python: >=3.8
License-File: LICENSE
Requires-Dist: numpy
Requires-Dist: pandas
Requires-Dist: linearmodels
